{
  "navigationBarTitleText": "我的店铺",
  "onReachBottomDistance": 10,
  "backgroundTextStyle": "light",
  "enablePullDownRefresh": true,
  "usingComponents": {
    "t-loading": "tdesign-miniprogram/loading/loading",
    "t-image": "tdesign-miniprogram/image/image",
    "t-icon": "tdesign-miniprogram/icon/icon",
    "t-toast": "tdesign-miniprogram/toast/toast",
    "t-tabs": "tdesign-miniprogram/tabs/tabs",
    "t-tab-panel": "tdesign-miniprogram/tab-panel/tab-panel",
    "goods-list": "/components/goods-list/index",
    "load-more": "/components/load-more/index",
    "floating-button": "/components/floating-button/index"
  }
}
